{
  "id": "2330402",
  "name": "JLpor",
  "font_family": "iconfont",
  "css_prefix_text": "icon-",
  "description": "",
  "glyphs": [
    {
      "icon_id": "1306",
      "name": "购物车空",
      "font_class": "gouwuchekong",
      "unicode": "e600",
      "unicode_decimal": 58880
    },
    {
      "icon_id": "1360",
      "name": "新浪微博",
      "font_class": "xinlangweibo",
      "unicode": "e601",
      "unicode_decimal": 58881
    },
    {
      "icon_id": "301413",
      "name": "在线服务-线",
      "font_class": "zaixianfuwuxian",
      "unicode": "e624",
      "unicode_decimal": 58916
    },
    {
      "icon_id": "436026",
      "name": "QQ空间",
      "font_class": "qqkongjian",
      "unicode": "e80f",
      "unicode_decimal": 59407
    },
    {
      "icon_id": "689226",
      "name": "店铺",
      "font_class": "dianpu",
      "unicode": "e7d6",
      "unicode_decimal": 59350
    },
    {
      "icon_id": "1166210",
      "name": "书本",
      "font_class": "shuben",
      "unicode": "e7a2",
      "unicode_decimal": 59298
    },
    {
      "icon_id": "1724906",
      "name": "返回顶部",
      "font_class": "fanhuidingbu",
      "unicode": "e612",
      "unicode_decimal": 58898
    },
    {
      "icon_id": "2053182",
      "name": "订单",
      "font_class": "dingdan",
      "unicode": "e6e4",
      "unicode_decimal": 59108
    },
    {
      "icon_id": "2468116",
      "name": "定位",
      "font_class": "dingwei",
      "unicode": "e610",
      "unicode_decimal": 58896
    },
    {
      "icon_id": "3050508",
      "name": "定位",
      "font_class": "location",
      "unicode": "e611",
      "unicode_decimal": 58897
    },
    {
      "icon_id": "3262862",
      "name": "心 爱心",
      "font_class": "xin",
      "unicode": "e623",
      "unicode_decimal": 58915
    },
    {
      "icon_id": "5044526",
      "name": "包包",
      "font_class": "baobao",
      "unicode": "e602",
      "unicode_decimal": 58882
    },
    {
      "icon_id": "5140599",
      "name": "维修",
      "font_class": "weixiu",
      "unicode": "e635",
      "unicode_decimal": 58933
    },
    {
      "icon_id": "5902997",
      "name": "帮助中心",
      "font_class": "bangzhuzhongxin",
      "unicode": "e627",
      "unicode_decimal": 58919
    },
    {
      "icon_id": "5982855",
      "name": "插头",
      "font_class": "chatou",
      "unicode": "ec77",
      "unicode_decimal": 60535
    },
    {
      "icon_id": "6240886",
      "name": "手机",
      "font_class": "shouji",
      "unicode": "e6ba",
      "unicode_decimal": 59066
    },
    {
      "icon_id": "6756291",
      "name": "微博",
      "font_class": "weibo",
      "unicode": "e608",
      "unicode_decimal": 58888
    },
    {
      "icon_id": "7064343",
      "name": "查询",
      "font_class": "zaitu",
      "unicode": "e60a",
      "unicode_decimal": 58890
    },
    {
      "icon_id": "8164415",
      "name": "下载",
      "font_class": "xiazai",
      "unicode": "e632",
      "unicode_decimal": 58930
    },
    {
      "icon_id": "8718273",
      "name": "搜索",
      "font_class": "sousuo",
      "unicode": "e609",
      "unicode_decimal": 58889
    },
    {
      "icon_id": "8897302",
      "name": "支付",
      "font_class": "zhifu",
      "unicode": "e66c",
      "unicode_decimal": 58988
    },
    {
      "icon_id": "10487467",
      "name": "汽车",
      "font_class": "qiche",
      "unicode": "e68e",
      "unicode_decimal": 59022
    },
    {
      "icon_id": "11518212",
      "name": "icon_左右箭头",
      "font_class": "icon_zuoyoujiantou",
      "unicode": "e60d",
      "unicode_decimal": 58893
    },
    {
      "icon_id": "13014641",
      "name": "人员",
      "font_class": "renyuan",
      "unicode": "e61a",
      "unicode_decimal": 58906
    }
  ]
}
